easy_images/__init__.py
easy_images/easy_images.py
easy_images_downloader-0.0.6.3.dist-info/LICENSE
easy_images_downloader-0.0.6.3.dist-info/METADATA
easy_images_downloader-0.0.6.3.dist-info/WHEEL
easy_images_downloader-0.0.6.3.dist-info/top_level.txt
easy_images_downloader-0.0.6.3.dist-info/RECORD
