Metadata-Version: 2.1
Name: easy-images-downloader
Version: 0.0.6.3
Summary: Download hundreds of images from Google. Do image post processing later.
Home-page: https://github.com/mohdsaqibhbi/easy_images.git
Author: Mohd Saqib
Author-email: mohdsaqibhbi@gmail.com
License: MIT
Download-URL: https://pypi.org/project/easy_images_downloader/
Keywords: easy images,easy images downloader,python image download,google images,image downloader
Platform: UNKNOWN
Requires-Dist: requests
Requires-Dist: opencv-python
Requires-Dist: beautifulsoup4
Requires-Dist: selenium
Requires-Dist: tqdm
Requires-Dist: webdriver-manager
Requires-Dist: tabulate
Requires-Dist: python-magic ; platform_system == "Linux"
Requires-Dist: python-magic-bin ; platform_system == "Windows"
